chrphb_contacts/__init__.py
chrphb_contacts/_modidx.py
chrphb_contacts/core.py
chrphb_contacts-0.0.1.dist-info/LICENSE
chrphb_contacts-0.0.1.dist-info/METADATA
chrphb_contacts-0.0.1.dist-info/WHEEL
chrphb_contacts-0.0.1.dist-info/entry_points.txt
chrphb_contacts-0.0.1.dist-info/top_level.txt
chrphb_contacts-0.0.1.dist-info/RECORD
